cgibbs_inf.cpython-37m-darwin.so
ktlda/__init__.py
ktlda/cgibbs_inf.cpython-37m-darwin.so
ktlda/facet.py
ktlda/model.py
ktlda/original.py
ktlda/utils.py
test/__init__.py
test/test_model.py
test/test_utils.py
ktLDA-0.0.6.dist-info/LICENSE
ktLDA-0.0.6.dist-info/METADATA
ktLDA-0.0.6.dist-info/WHEEL
ktLDA-0.0.6.dist-info/top_level.txt
ktLDA-0.0.6.dist-info/RECORD
