Metadata-Version: 2.1
Name: ktLDA
Version: 0.0.6
Summary: An implementation of latent Dirichlet allocation
Home-page: https://github.com/cPolaris/ktLDA
Author: Kehan (kehanLyu) & Tiangang (cPolaris)
Author-email: 
License: UNKNOWN
Platform: UNKNOWN
Classifier: Programming Language :: Python :: 3
Classifier: License :: OSI Approved :: MIT License
Classifier: Operating System :: OS Independent
